chaukas/sdk/__init__.py
chaukas/sdk/core/__init__.py
chaukas/sdk/core/agent_mapper.py
chaukas/sdk/core/client.py
chaukas/sdk/core/config.py
chaukas/sdk/core/event_builder.py
chaukas/sdk/core/proto_wrapper.py
chaukas/sdk/core/tracer.py
chaukas/sdk/integrations/__init__.py
chaukas/sdk/integrations/base.py
chaukas/sdk/integrations/crewai.py
chaukas/sdk/integrations/google_adk.py
chaukas/sdk/integrations/openai_agents.py
chaukas/sdk/utils/__init__.py
chaukas/sdk/utils/context.py
chaukas/sdk/utils/event_pairs.py
chaukas/sdk/utils/monkey_patch.py
chaukas/sdk/utils/retry_detector.py
chaukas/sdk/utils/uuid7.py
chaukas_sdk-0.1.0.dist-info/licenses/LICENSE
chaukas_sdk-0.1.0.dist-info/licenses/NOTICE
chaukas_sdk-0.1.0.dist-info/METADATA
chaukas_sdk-0.1.0.dist-info/WHEEL
chaukas_sdk-0.1.0.dist-info/top_level.txt
chaukas_sdk-0.1.0.dist-info/RECORD
