Metadata-Version: 2.4
Name: chaukas-sdk
Version: 0.1.0
Summary: One-line instrumentation for agent building SDKs
Author-email: Chaukas <2153483+ranesidd@users.noreply.github.com>
License: Apache License
Project-URL: Homepage, https://chaukas.ai
Project-URL: Repository, https://github.com/chaukasai/chaukas-sdk
Project-URL: Documentation, https://github.com/chaukasai/chaukas-sdk#readme
Project-URL: Issues, https://github.com/chaukasai/chaukas-sdk/issues
Project-URL: Changelog, https://github.com/chaukasai/chaukas-sdk/blob/main/CHANGELOG.md
Project-URL: Spec, https://github.com/chaukasai/chaukas-spec
Keywords: ai,agents,observability,instrumentation,tracing,openai,crewai,langchain,monitoring,telemetry,llm,agentic,chaukas-spec
Classifier: Development Status :: 3 - Alpha
Classifier: Intended Audience :: Developers
Classifier: License :: OSI Approved :: Apache Software License
Classifier: Programming Language :: Python :: 3
Classifier: Programming Language :: Python :: 3.9
Classifier: Programming Language :: Python :: 3.10
Classifier: Programming Language :: Python :: 3.11
Classifier: Programming Language :: Python :: 3.12
Classifier: Topic :: Software Development :: Libraries :: Python Modules
Classifier: Topic :: System :: Monitoring
Requires-Python: >=3.9
License-File: LICENSE
License-File: NOTICE
Requires-Dist: chaukas-spec-client>=1.0.0
Requires-Dist: wrapt>=1.14.0
Requires-Dist: pydantic>=2.0.0
Requires-Dist: httpx>=0.24.0
Requires-Dist: typing-extensions>=4.0.0
Requires-Dist: protobuf>=5.26.0
Requires-Dist: grpcio>=1.50.0
Requires-Dist: uuid6>=2024.1.12
Requires-Dist: aiofiles>=23.0.0
Provides-Extra: openai
Requires-Dist: openai-agents<1.0.0,>=0.5.0; extra == "openai"
Provides-Extra: google
Requires-Dist: adk; extra == "google"
Provides-Extra: crewai
Requires-Dist: crewai<2.0.0,>=1.4.1; extra == "crewai"
Provides-Extra: dev
Requires-Dist: pytest>=7.0.0; extra == "dev"
Requires-Dist: pytest-asyncio>=0.21.0; extra == "dev"
Requires-Dist: pytest-mock>=3.10.0; extra == "dev"
Requires-Dist: black>=23.0.0; extra == "dev"
Requires-Dist: isort>=5.12.0; extra == "dev"
Requires-Dist: mypy>=1.0.0; extra == "dev"
Dynamic: license-file
